MANIFEST.in
README.rst
setup.py
pylatest/__init__.py
pylatest/document.py
pylatest/export.py
pylatest/main.py
pylatest/pysource.py
pylatest/rstsource.py
pylatest/template.py
pylatest.egg-info/PKG-INFO
pylatest.egg-info/SOURCES.txt
pylatest.egg-info/dependency_links.txt
pylatest.egg-info/entry_points.txt
pylatest.egg-info/requires.txt
pylatest.egg-info/top_level.txt
pylatest/templates/testcase.rst
pylatest/xdocutils/__init__.py
pylatest/xdocutils/core.py
pylatest/xdocutils/directives.py
pylatest/xdocutils/htmltranslator.py
pylatest/xdocutils/nodes.py
pylatest/xdocutils/readers.py
pylatest/xdocutils/roles.py
pylatest/xdocutils/transforms.py
pylatest/xdocutils/utils.py
pylatest/xsphinx/__init__.py
pylatest/xsphinx/builders.py
pylatest/xsphinx/extension.py
pylatest/xsphinx/pylatest.css
tests/test_document.py
tests/test_export.py
tests/test_rstsource.py
tests/pysource/test_pysource.py
tests/pysource/pysource-multiplecasesperfile/testcase.none.rst
tests/pysource/pysource-multiplecasesperfile/testcase.splitted-nested-default-override-null.py
tests/pysource/pysource-multiplecasesperfile/testcase.splitted-nested-default-override.py
tests/pysource/pysource-multiplecasesperfile/testcase.splitted-nested-default.py
tests/pysource/pysource-multiplecasesperfile/testcase.splitted-nested.py
tests/pysource/pysource-multiplecasesperfile/testcase.test01.rst
tests/pysource/pysource-multiplecasesperfile/testcase.test02.rst
tests/pysource/pysource-multiplecasesperfile/testcase.test03.rst
tests/pysource/pysource-onecaseperfile/testcase.descriptionmissing-setupmissing.rst
tests/pysource/pysource-onecaseperfile/testcase.descriptionmissing.rst
tests/pysource/pysource-onecaseperfile/testcase.null.py
tests/pysource/pysource-onecaseperfile/testcase.rst
tests/pysource/pysource-onecaseperfile/testcase.setupmissing.rst
tests/pysource/pysource-onecaseperfile/testcase.single-descriptionmissing-setupmissing.py
tests/pysource/pysource-onecaseperfile/testcase.single-descriptionmissing.py
tests/pysource/pysource-onecaseperfile/testcase.single-setupmissing.py
tests/pysource/pysource-onecaseperfile/testcase.single-stepsmissing-teardownmissing.py
