Metadata-Version: 1.1
Name: pylatest
Version: 0.1.4
Summary: Testcase description management tools.
Home-page: http://gitlab.com/mbukatov/pylatest/
Author: Martin Bukatovič
Author-email: mbukatov@redhat.com
License: GPLv3
Platform: UNKNOWN
Classifier: Development Status :: 3 - Alpha
Classifier: Topic :: Software Development :: Quality Assurance
Classifier: Topic :: Utilities
Classifier: Topic :: Text Processing :: Markup
Classifier: Programming Language :: Python :: 2.7
Classifier: Programming Language :: Python :: 3
Classifier: Programming Language :: Python :: 3.6
